freaddb/__init__.py
freaddb/db_lmdb.py
freaddb-0.0.9.dist-info/WHEEL
freaddb-0.0.9.dist-info/METADATA
freaddb-0.0.9.dist-info/RECORD
