Metadata-Version: 2.1
Name: freaddb
Version: 0.0.9
Summary: Fast Read DB
Home-page: https://github.com/phucty/freaddb
License: MIT and The OpenLDAP Public License
Author: Phuc Nguyen
Author-email: phucnt.ty@gmail.com
Requires-Python: >=3.8,<4.0
Classifier: License :: Other/Proprietary License
Classifier: Programming Language :: Python :: 3
Classifier: Programming Language :: Python :: 3.10
Classifier: Programming Language :: Python :: 3.8
Classifier: Programming Language :: Python :: 3.9
Requires-Dist: lmdb (>=1.3.0,<2.0.0)
Requires-Dist: lz4 (>=4.0.1,<5.0.0)
Requires-Dist: msgpack (>=1.0.4,<2.0.0)
Requires-Dist: numpy (>=1.22.4,<2.0.0)
Requires-Dist: psutil (>=5.9.4,<6.0.0)
Requires-Dist: pyroaring (>=0.3.3,<0.4.0)
Requires-Dist: tqdm (>=4.64.0,<5.0.0)
Requires-Dist: ujson (>=5.3.0,<6.0.0)
Project-URL: Repository, https://github.com/phucty/freaddb
